mnist_utils/__init__.py
mnist_utils/utils.py
mnist_utils/test/__init__.py
mnist_utils/test/test.py
mnist_utils-0.0.2.dist-info/LICENSE
mnist_utils-0.0.2.dist-info/METADATA
mnist_utils-0.0.2.dist-info/WHEEL
mnist_utils-0.0.2.dist-info/top_level.txt
mnist_utils-0.0.2.dist-info/RECORD
