Metadata-Version: 2.1
Name: mnist-utils
Version: 0.0.2
Summary: A small package for working with MNIST data.
Home-page: https://github.com/raghavp96/mnist_utils
Author: Raghavprasanna Rajagopalan
Author-email: raghavp96@gmail.com
License: UNKNOWN
Platform: UNKNOWN
Classifier: Programming Language :: Python :: 3
Classifier: License :: OSI Approved :: MIT License
Classifier: Operating System :: OS Independent
Requires-Python: >=3.6
Requires-Dist: numpy (>=1.19.0)
Requires-Dist: matplotlib (>=3.2.2)
